aiooui/__init__.py
aiooui/oui.data
aiooui/py.typed
aiooui-0.1.9.dist-info/LICENSE
aiooui-0.1.9.dist-info/METADATA
aiooui-0.1.9.dist-info/WHEEL
aiooui-0.1.9.dist-info/top_level.txt
aiooui-0.1.9.dist-info/RECORD
