Metadata-Version: 2.3
Name: aiooui
Version: 0.1.9
Summary: Async OUI lookups
License: MIT
Author: J. Nick Koston
Author-email: nick@koston.org
Requires-Python: >=3.9,<4.0
Classifier: Development Status :: 2 - Pre-Alpha
Classifier: Intended Audience :: Developers
Classifier: License :: OSI Approved :: MIT License
Classifier: Natural Language :: English
Classifier: Operating System :: OS Independent
Classifier: Programming Language :: Python :: 3
Classifier: Programming Language :: Python :: 3.9
Classifier: Programming Language :: Python :: 3.10
Classifier: Programming Language :: Python :: 3.11
Classifier: Programming Language :: Python :: 3.12
Classifier: Programming Language :: Python :: 3.13
Classifier: Topic :: Software Development :: Libraries
Project-URL: Bug Tracker, https://github.com/bluetooth-devices/aiooui/issues
Project-URL: Changelog, https://github.com/bluetooth-devices/aiooui/blob/main/CHANGELOG.md
Project-URL: Repository, https://github.com/bluetooth-devices/aiooui
